napari_vodex/__init__.py
napari_vodex/_controller.py
napari_vodex/_model.py
napari_vodex/_version.py
napari_vodex/_view.py
napari_vodex/_widget.py
napari_vodex/napari.yaml
napari_vodex/_tests/__init__.py
napari_vodex/_tests/test_VodexModel.py
napari_vodex/_tests/test_widget.py
napari_vodex-1.0.12.dist-info/LICENSE
napari_vodex-1.0.12.dist-info/METADATA
napari_vodex-1.0.12.dist-info/WHEEL
napari_vodex-1.0.12.dist-info/entry_points.txt
napari_vodex-1.0.12.dist-info/top_level.txt
napari_vodex-1.0.12.dist-info/RECORD
