Metadata-Version: 2.1
Name: napari-vodex
Version: 1.0.12
Summary: A napari plugin for VoDEx : Volumetric Data and Experiment Manager. Allows to load volumetric data based on experimental conditions.
Home-page: https://github.com/LemonJust/napari-vodex
Author: Anna Nadtochiy
Author-email: lemonjustgithub@gmail.com
License: BSD-3-Clause
Project-URL: Bug Tracker, https://github.com/LemonJust/napari-vodex/issues
Project-URL: Documentation, https://lemonjust.github.io/vodex/napari/
Project-URL: Source Code, https://github.com/LemonJust/napari-vodex
Project-URL: User Support, https://github.com/LemonJust/napari-vodex/issues
Classifier: Development Status :: 3 - Alpha
Classifier: Framework :: napari
Classifier: Intended Audience :: Developers
Classifier: License :: OSI Approved :: BSD License
Classifier: Operating System :: OS Independent
Classifier: Programming Language :: Python
Classifier: Programming Language :: Python :: 3
Classifier: Programming Language :: Python :: 3 :: Only
Classifier: Programming Language :: Python :: 3.8
Classifier: Programming Language :: Python :: 3.9
Classifier: Programming Language :: Python :: 3.10
Classifier: Topic :: Scientific/Engineering :: Image Processing
Requires-Python: >=3.8
License-File: LICENSE
Requires-Dist: vodex (>=1.0.12)
Requires-Dist: numpy
Requires-Dist: magicgui
Requires-Dist: qtpy
Provides-Extra: testing
Requires-Dist: tox ; extra == 'testing'
Requires-Dist: pytest ; extra == 'testing'
Requires-Dist: pytest-cov ; extra == 'testing'
Requires-Dist: pytest-qt ; extra == 'testing'
Requires-Dist: napari ; extra == 'testing'
Requires-Dist: pyqt5 ; extra == 'testing'
